README.md
setup.py
sysmor/__init__.py
sysmor/aaa.py
sysmor/cauchy.py
sysmor/check_der.py
sysmor/demos.py
sysmor/h2mor.py
sysmor/irka.py
sysmor/lagrange.py
sysmor/marriage.py
sysmor/optfit.py
sysmor/pbfit.py
sysmor/pffit.py
sysmor/pgf.py
sysmor/ph2.py
sysmor/quadvf.py
sysmor/ratfit.py
sysmor/skfit.py
sysmor/subspace.py
sysmor/system.py
sysmor/tfirka.py
sysmor/vecfit.py
sysmor.egg-info/PKG-INFO
sysmor.egg-info/SOURCES.txt
sysmor.egg-info/dependency_links.txt
sysmor.egg-info/requires.txt
sysmor.egg-info/top_level.txt