Metadata-Version: 1.2
Name: sysmor
Version: 0.1
Summary: System-Theoertic Model Order Reduction
Home-page: UNKNOWN
Author: Jeffrey M. Hokanson
License: UNKNOWN
Platform: UNKNOWN
Requires-Python: >=3.6
